InstallMyScript/__init__.py
InstallMyScript/setup.py
InstallMyScript-0.0.2.dist-info/LICENSE.txt
InstallMyScript-0.0.2.dist-info/METADATA
InstallMyScript-0.0.2.dist-info/WHEEL
InstallMyScript-0.0.2.dist-info/top_level.txt
InstallMyScript-0.0.2.dist-info/RECORD
