Metadata-Version: 2.1
Name: InstallMyScript
Version: 0.0.2
Summary: adding two numbers
Home-page: UNKNOWN
Author: Vijay kumar Bestha
Author-email: Someone@domain.com
License: UNKNOWN
Platform: UNKNOWN
Classifier: Programming Language :: Python :: 3
Classifier: License :: OSI Approved :: MIT License
Classifier: Operating System :: OS Independent
